JuanAcuna_calc/__init__.py
juanacuna_calc-0.1.0.dist-info/licenses/LICENSE
juanacuna_calc-0.1.0.dist-info/METADATA
juanacuna_calc-0.1.0.dist-info/WHEEL
juanacuna_calc-0.1.0.dist-info/top_level.txt
juanacuna_calc-0.1.0.dist-info/RECORD
