Metadata-Version: 2.4
Name: JuanAcuna-Calc
Version: 0.1.0
Summary: La mejor calculadora nunca antes vista.
Author-email: Juan Sebastian Acuña Tellez <jsacunat@udistrital.edu.co>
License: Universidad Distrital License
Project-URL: Homepage, https://github.com/tu_usuario/JuanAcunaCalc
Classifier: Programming Language :: Python :: 3
Classifier: License :: OSI Approved :: MIT License
Classifier: Operating System :: OS Independent
Requires-Python: >=3.8
License-File: LICENSE
Requires-Dist: tensorflow
Dynamic: license-file
